[
  {
    "id": "8bcc5bfb-0271-4f71-866f-547367407a55",
    "data": [
      {
        "text": "selam",
        "userDefined": false
      }
    ],
    "isTemplate": false,
    "count": 0,
    "lang": "tr",
    "updated": 0
  },
  {
    "id": "42b7cc38-c29b-40fa-b3ee-ba6dbbe505fb",
    "data": [
      {
        "text": "ne güzel bir gün değil mi",
        "userDefined": false
      }
    ],
    "isTemplate": false,
    "count": 0,
    "lang": "tr",
    "updated": 0
  },
  {
    "id": "ad64d0cd-bf5c-47a4-990b-76758cd1eb56",
    "data": [
      {
        "text": "selam naber",
        "userDefined": false
      }
    ],
    "isTemplate": false,
    "count": 0,
    "lang": "tr",
    "updated": 0
  },
  {
    "id": "96173ed4-5a73-44f3-af2f-8bef164b1bb5",
    "data": [
      {
        "text": "merhaba",
        "userDefined": false
      }
    ],
    "isTemplate": false,
    "count": 0,
    "lang": "tr",
    "updated": 0
  },
  {
    "id": "5af097e3-9d64-46aa-8ebf-9b96a155b062",
    "data": [
      {
        "text": "selam dostum",
        "userDefined": false
      }
    ],
    "isTemplate": false,
    "count": 0,
    "lang": "tr",
    "updated": 0
  },
  {
    "id": "a159df95-ae19-45a0-8780-8c9b4dd2ffcc",
    "data": [
      {
        "text": "tünaydın",
        "userDefined": false
      }
    ],
    "isTemplate": false,
    "count": 0,
    "lang": "tr",
    "updated": 0
  },
  {
    "id": "a964b2e6-2490-48ec-9fba-7489d7bd636f",
    "data": [
      {
        "text": "seni selamlıyorum",
        "userDefined": false
      }
    ],
    "isTemplate": false,
    "count": 0,
    "lang": "tr",
    "updated": 0
  },
  {
    "id": "c80db204-ed93-4c01-9414-41152ae49271",
    "data": [
      {
        "text": "yüzünü gören cennetlik",
        "userDefined": false
      }
    ],
    "isTemplate": false,
    "count": 0,
    "lang": "tr",
    "updated": 0
  },
  {
    "id": "e3c1a92b-810b-4dc6-91b4-4822808a0c92",
    "data": [
      {
        "text": "merhaba naber",
        "userDefined": false
      }
    ],
    "isTemplate": false,
    "count": 0,
    "lang": "tr",
    "updated": 0
  },
  {
    "id": "c862a2a2-4ddf-4fd2-a9d0-3f584e0d76f9",
    "data": [
      {
        "text": "hey",
        "userDefined": false
      }
    ],
    "isTemplate": false,
    "count": 0,
    "lang": "tr",
    "updated": 0
  },
  {
    "id": "39f5ae0a-d21e-4f2a-bdb8-733540279d78",
    "data": [
      {
        "text": "iyi günler",
        "userDefined": false
      }
    ],
    "isTemplate": false,
    "count": 0,
    "lang": "tr",
    "updated": 0
  },
  {
    "id": "b2e47910-85bb-4c03-85cf-564b7f452d81",
    "data": [
      {
        "text": "selamlar",
        "userDefined": false
      }
    ],
    "isTemplate": false,
    "count": 0,
    "lang": "tr",
    "updated": 0
  },
  {
    "id": "24d63a08-4a35-4de1-a0c0-dda843668d73",
    "data": [
      {
        "text": "selam sana",
        "userDefined": false
      }
    ],
    "isTemplate": false,
    "count": 0,
    "lang": "tr",
    "updated": 0
  },
  {
    "id": "ee62a2b2-61ae-473c-a232-d8e1d2f2c6e1",
    "data": [
      {
        "text": "tekrar merhaba",
        "userDefined": false
      }
    ],
    "isTemplate": false,
    "count": 0,
    "lang": "tr",
    "updated": 0
  },
  {
    "id": "ef0ff4bc-2a3f-4d45-86a9-f9b36725069f",
    "data": [
      {
        "text": "selam merhaba",
        "userDefined": false
      }
    ],
    "isTemplate": false,
    "count": 0,
    "lang": "tr",
    "updated": 0
  },
  {
    "id": "76566227-8ad7-4933-a81a-11793c2f6f8f",
    "data": [
      {
        "text": "naber",
        "userDefined": false
      }
    ],
    "isTemplate": false,
    "count": 0,
    "lang": "tr",
    "updated": 0
  },
  {
    "id": "8a81d0cd-3a62-404b-9b76-e8317b1f08f0",
    "data": [
      {
        "text": "merhaba demek istedim",
        "userDefined": false
      }
    ],
    "isTemplate": false,
    "count": 0,
    "lang": "tr",
    "updated": 0
  },
  {
    "id": "b4933b55-3579-48c7-9c48-a840a4703be9",
    "data": [
      {
        "text": "merhabalar",
        "userDefined": false
      }
    ],
    "isTemplate": false,
    "count": 0,
    "lang": "tr",
    "updated": 0
  }
]